{"data":{"allFile":{"edges":[{"node":{"relativePath":"state/createStore.js","prettySize":"356 B","extension":"js","birthTime":"21 hours ago"}},{"node":{"relativePath":"components/container.js","prettySize":"210 B","extension":"js","birthTime":"21 hours ago"}},{"node":{"relativePath":"post/post1.md","prettySize":"555 B","extension":"md","birthTime":"21 hours ago"}},{"node":{"relativePath":"components/header.js","prettySize":"1.35 kB","extension":"js","birthTime":"21 hours ago"}},{"node":{"relativePath":"components/layout.js","prettySize":"1.04 kB","extension":"js","birthTime":"21 hours ago"}},{"node":{"relativePath":"components/image.js","prettySize":"1.02 kB","extension":"js","birthTime":"21 hours ago"}},{"node":{"relativePath":"pages/404.js","prettySize":"489 B","extension":"js","birthTime":"21 hours ago"}},{"node":{"relativePath":"pages/my-files.js","prettySize":"1.08 kB","extension":"js","birthTime":"21 hours ago"}},{"node":{"relativePath":"pages/posts.js","prettySize":"1.35 kB","extension":"js","birthTime":"21 hours ago"}},{"node":{"relativePath":"pages/index.js","prettySize":"1.02 kB","extension":"js","birthTime":"21 hours ago"}},{"node":{"relativePath":"templates/blog-post.js","prettySize":"1.15 kB","extension":"js","birthTime":"21 hours ago"}},{"node":{"relativePath":"styles/base.scss","prettySize":"323 B","extension":"scss","birthTime":"8 minutes ago"}},{"node":{"relativePath":"styles/reset.scss","prettySize":"1.23 kB","extension":"scss","birthTime":"8 minutes ago"}},{"node":{"relativePath":"styles/typography.scss","prettySize":"395 B","extension":"scss","birthTime":"7 minutes ago"}},{"node":{"relativePath":"utils/typography.js","prettySize":"161 B","extension":"js","birthTime":"21 hours ago"}},{"node":{"relativePath":"post/post2.md","prettySize":"431 B","extension":"md","birthTime":"21 hours ago"}},{"node":{"relativePath":"assets/images/gatsby-icon.png","prettySize":"21.2 kB","extension":"png","birthTime":"21 hours ago"}},{"node":{"relativePath":"post/post3.md","prettySize":"388 B","extension":"md","birthTime":"21 hours ago"}},{"node":{"relativePath":"assets/images/gatsby-astronaut.png","prettySize":"167 kB","extension":"png","birthTime":"21 hours ago"}}]}},"pageContext":{}}